Metadata-Version: 2.1
Name: rokkket
Version: 1.0.0
Summary: An awesome package that only allows you to create rockets
Home-page: http://pypi.python.org/pypi/rocket
Author: DJEBARRA Rabah Abderrazak
Author-email: djebarra.ra@gmail.com
License: LICENSE.txt
License-File: LICENSE.txt
